download_searchcode_files/__init__.py
download_searchcode_files/core.py
download_stackoverflow_codesnippets/__init__.py
download_stackoverflow_codesnippets/core.py
download_stackoverflow_codesnippets/so_helper.py
extract_line_from_files/__init__.py
extract_line_from_files/core.py
moss_client/__init__.py
moss_client/core.py
moss_client/dl_helper.py
Py_SCSO_Compare-1.0.1.dist-info/LICENSE
Py_SCSO_Compare-1.0.1.dist-info/METADATA
Py_SCSO_Compare-1.0.1.dist-info/WHEEL
Py_SCSO_Compare-1.0.1.dist-info/top_level.txt
Py_SCSO_Compare-1.0.1.dist-info/RECORD
