Metadata-Version: 2.1
Name: Py-SCSO-Compare
Version: 1.0.1
Summary: Search and download Java files that contain StackOverflow links from Searchcode, and compare them with code snippets from StackOverflow questions or answers.
Home-page: https://github.com/mernst32/Py-SCSO-Compare
Author: Maximilian Ernst
Author-email: mernst32@yahoo.com
License: UNKNOWN
Platform: UNKNOWN
Classifier: Programming Language :: Python :: 3
Classifier: License :: OSI Approved :: MIT License
Classifier: Operating System :: OS Independent
Classifier: Development Status :: 5 - Production/Stable
Classifier: Environment :: Console
Requires-Python: >=3.6
